Workbook

Sheet SUMMERY
A1: Taffy Casa Luz
A2: Income | D2: Expenses
A3: Opening Balance | B3: =+[1]RECON!$C$4 -> -456526.24
A4: January | B4: =+[1]INCOME!$D$51 -> 812375 | D4: January | E4: =+'INCOME VS EXPENSES'!D8 -> 183410.17
A5: February | B5: =5000*67 -> 335000 | D5: February | E5: =+'INCOME VS EXPENSES'!D9 -> 200316.44
A6: March | D6: March | E6: =+'INCOME VS EXPENSES'!D10 -> 0
A7: April | D7: April | E7: =+'INCOME VS EXPENSES'!D11 -> 0
A8: May | D8: May | E8: =+'INCOME VS EXPENSES'!D12 -> 0
A9: June | D9: June | E9: =+'INCOME VS EXPENSES'!D13 -> 0
A10: July | D10: July | E10: =+'INCOME VS EXPENSES'!D14 -> 0
A11: August | D11: August | E11: =+'INCOME VS EXPENSES'!D15 -> 0
A12: September | D12: September | E12: =+'INCOME VS EXPENSES'!D16 -> 0
A13: October | D13: October | E13: =+'INCOME VS EXPENSES'!D17 -> 0
A14: November | D14: November | E14: =+'INCOME VS EXPENSES'!D18 -> 0
A15: December | D15: December | E15: =+'INCOME VS EXPENSES'!D19 -> 0
A16: Total | B16: =SUM(B3:B15) -> 690848.76 | D16: Total | E16: =SUM(E4:E15) -> 383726.61
B17: =+B16/67 -> 10311.175
A19: BALANCE AVAILIBLE | E19: =+B16-E16 -> 307122.15
A20: RATE 63,25 | E20: =+E19/63.25 -> 4855.6861
A21: PLEASE TOP UP WITH $10000

Sheet Breakdown of Income
B1: BREAKDOWN OF INCOME 2026
B2: DESCRIPTION | C2: MTS | D2: USD | E2: RATE
A3: JANUARY | B3: OPENING BALANCE JAN | C3: =+'INCOME VS EXPENSES'!D6 -> -456526.24 | D3: =+C3/E3 -> -7217.8062 | E3: 63.25
A4: JANUARY | B4: CASH FROM TAFY | C4: =+[1]INCOME!$D$51 -> 812375 | D4: =+C4/E4 -> 12125 | E4: 67 | F4: PAID $1375 TOWARDS BURGLARY
A5: FEBRUARY | B5: CASH FROM TAFY | C5: =+D5*E5 -> 335000 | D5: 5000 | E5: 67
A6: MARCH
A7: APRIL
A8: MAY
A9: JUNE
A10: JULY
A11: AUGUST
A12: SEPTEMBER
A13: OCTOBER
A14: NOVEMBER
A15: DECEMBER
B16: TOTAL INCOME FOR 2026 | C16: =SUM(C4:C15) -> 1147375 | D16: =SUM(D4:D15) -> 17125

Sheet INCOME VS EXPENSES
A2: INCOME VS EXPENSES | C2: TOTAL OF ALL INCOME - ALL EXPENSES
B4: MZN
A5: PERSONAL INCOME BALANCE | B5: =+D6+D7 -> 690848.76 | D5: MZN
A6: TOTAL EXPENSES | B6: =SUM(D8:D19) -> 383726.61 | C6: PERSONAL BALANCE CARRIED FORWARD DEC 2025 | D6: =+[2]SUMMERY!$E$19 -> -456526.24
A7: BALANCE | B7: =+B5-B6 -> 307122.15 | C7: PERSONAL LANDCO INCOME DRAWN FROM 01 JAN 2025 | D7: =+'Breakdown of Income'!C16 -> 1147375
C8: EXPENSES JANUARY | D8: 183410.17
C9: EXPENSES FEBUARY | D9: 200316.44
A10: SHARED EXPENSES | B10: =+' Expenses '!D24 -> 162772.73 | C10: EXPENSES MARCH
A11: PERSONAL EXPENSES | B11: =+' Expenses '!D30 -> 37543.707 | C11: EXPENSES APRIL
A12: TOTAL EXPENSES JAN | B12: =SUM(B10:B11) -> 200316.44 | C12: EXPENSES MAY
C13: EXPENSES JUNE
C14: EXPENSES JULY
C15: EXPENSES AUGUST
C16: EXPENSES SEPTEMBER
C17: EXPENSES OCTOBER
C18: EXPENSES NOVEMBER
C19: EXPENSES DECEMBER
C21: TOTAL I/E LEFTOVER | D21: =+D6+D7-D8-D9-D10-D11-D12-D13-D14-D15-D16-D17-D18-D19 -> 307122.15
D24: =SUM(D8:D18) -> 383726.61

Sheet  Expenses 
C2: SHARED EXPENCES | D2: =+D24 -> 162772.73
C3: PERSONAL EXPENCES | D3: =+D30 -> 37543.707
C4: TOTAL EXPENCES | D4: =SUM(D2:D3) -> 200316.44
C5: PERSONAL AND SHARED EXPENSES | D5: 46023
B6: SHARED | C6: DEACRIPTION | D6: Mets
B7: SHARED | C7: SALARIES & WAGES | D7: 80075.288
B8: SHARED | C8: CASUAL WORKERS AND FOOD ALLOWANCE | D8: 5250
B9: SHARED | C9: OFFICE AND BANK CHARGES | D9: 986.5
B10: SHARED | C10: ADMIN CHARGES (BDO & ANDRISA ENS ) | D10: 46031.7
B11: SHARED | C11: GAS AND ELECTRISITY | D11: 15723.775
B12: SHARED | C12: MAINTENANCE GENERAL | D12: 6068.4
B13: SHARED | C13: MAINTENANCE GARDEN & POOL | D13: 606.15
B14: SHARED | C14: SMALL TOOLS | D14: 0
B15: SHARED | C15: EQUIPMENT PRESSURE PUMP X 2 | D15: 0
B16: SHARED | C16: MAINTENANCE VEHICLES | D16: 0
B17: SHARED | C17: INSURANCE & LICENSE | D17: 1281.42
B18: SHARED | C18: DIESEL AND PETROL | D18: 3565.75
... B21: SHARED | C21: COMMUNITY DONATION | D21: 0
B22: SHARED
D24: =SUBTOTAL(9,D7:D23) -> 162772.73
B25: PERSONAL | C25: LUZ STAFF SALARIES | D25: =+'[3] EXPENSES HOUSE'!$D$4 -> 36513.707
B26: PERSONAL | C26: SKIPPERS BOAT CLEANING | D26: =+'[3] EXPENSES HOUSE'!$F$4 -> 0
B27: PERSONAL | C27: BOAT CLEANING MATERIAL | D27: =+'[3] EXPENSES HOUSE'!$G$4 -> 0
B28: PERSONAL | C28: HOUSE KEEPING CLEANING MATERIAL | D28: =+'[3] EXPENSES HOUSE'!$H$4 -> 1030
B29: PERSONAL
D30: =SUBTOTAL(9,D25:D29) -> 37543.707

Sheet Sheet1
