Workbook

Sheet INCOME
A1: LANDCO INCOME | D1: H1 | E1: =+#REF! -> #REF! | F1: =+E1/63.25 -> #REF!
D2: H2 | E2: =+#REF! -> #REF! | F2: =+E2/63.25 -> #REF!
D3: H3 | E3: =+#REF! -> #REF! | F3: =+E3/63.25 -> #REF!
D4: H4 | E4: =+#REF! -> #REF! | F4: =+E4/63.25 -> #REF!
E5: =SUM(E1:E4) -> #REF! | F5: =+E5/63.25 -> #REF! | G5: =SUM(F1:F4) -> #REF!
A6: DATE | B6: HOUSE | C6: NAME | D6: ACCOMODATION | E6: H1 | F6: H2 | G6: H3 | H6: H4 | I6: TOTAL MTS | J6: DOLLARS | K6: TOTAL PER MONTH
A7: 46113 | B7: 1 | C7: TAFY ELIANA | D7: 38400 | E7: 38400 | J7: =+D7/63.25 -> 607.11462
A8: 46120 | B8: 3 | C8: ALEX DEP BANK | D8: 733700 | G8: =+D8 -> 733700 | J8: =+D8/63.25 -> 11600
A9: 46134 | B9: 4 | C9: GAVIN FOR H4 | D9: =5500*68 -> 374000 | H9: =+D9 -> 374000 | J9: 5500
A10: 46140 | B10: 1 | C10: TAFY | D10: =10000*68 -> 680000 | E10: =+D10 -> 680000 | J10: 10000
A11: 46140 | B11: 1 | C11: ROBIN FOR TAFY | D11: =3000*68 -> 204000 | E11: =+D11 -> 204000 | J11: =+D11/63.25 -> 3225.2964

Sheet RECON
D1: 46113
C3: BALANCE END MARCH | D3: INCOME APRIL | E3: EXPENSES APRIL | F3: TOTAL END APRIL
B4: CASA LUZ | C4: =+[1]SUMMERY!$E$19 -> 99370.136 | D4: =13000*68+38400 -> 922400 | E4: =+' EXPENSES HOUSE'!M4 -> #REF! | F4: =+C4+D4-E4 -> #REF! | H4: =+F4-C21 -> #REF!
B5: CASA AURORA | C5: =+'[2] SUMMERY '!$F$19 -> 197931.38 | E5: =+' EXPENSES HOUSE'!M5 -> 290384.12 | F5: =+C5+D5-E5 -> -92452.738 | H5: =+F5-C22 -> -290384.12
B6: CASA CAJU | C6: =+[3]SUMMERY!$F$19 -> 773264.78 | D6: 733700 | E6: =+' EXPENSES HOUSE'!M6 -> 267794.73 | F6: =+C6+D6-E6 -> 1239170.1 | H6: =+F6-C23 -> 465905.27
B7: CASA COCO | C7: =+'[4]SUMMERY '!$F$19 -> 878066.8 | D7: =5500*68 -> 374000 | E7: =+' EXPENSES HOUSE'!M7 -> 363859.04 | F7: =+C7+D7-E7 -> 888207.76 | H7: =+F7-C24 -> 10140.96
B8: NEGU | C8: 170900 | F8: =+C8+D8-E8 -> 170900
B9: Total | C9: 1187373 | D9: =SUM(D4:D7) -> 2030100 | E9: =SUM(E4:E7) -> #REF! | F9: =SUM(F4:F8) -> #REF!
B11: SHAREHOLDERS | D11: ADD INCOME | G11: PETTY CASH | I11: BANK/PRE-PAID & $
C12: =+C9 -> 1187373 | F12: OPEN BALANCE | G12: =+'[5]LANDCO MET CASH'!$F$9+335000 -> 688506.96 | I12: =+'[6]BIM Bank Control USD'!$J$3+'[6]BIM Bank Control Mtn'!$J$2+'[6]Petty cash '!$G$4+'[6]Pre-paid'!$G$4 -> 498865.79 | K12: =+C12-G12-I12 -> 0.2383
C13: =+D9 -> 2030100 | F13: INCOME | I13: =+D9 -> 2030100 | K13: =+C13-G13-I13+J13 -> 0
F14: ADD INCOME | K14: =+C14-G14+I14 -> 0
K15: =+C15-G15-I15 -> 0
B16: =+E9 -> #REF! | F16: PAYMENTS | H16: =+'[7]LANDCO MET CASH'!$F$8 -> 213314 | J16: =+' EXPENSES'!D2 -> 954875.91 | K16: =+B16-H16-J16 -> #REF!
B17: =+F9 -> #REF! | F17: BALANCE | H17: =+'[7]LANDCO MET CASH'!$F$9+335000 -> 475192.96 | J17: =+'[6]BIM Bank Control USD'!$J$7+'[6]BIM Bank Control Mtn'!$J$6+'[6]Petty cash '!$G$8+'[6]Pre-paid'!$G$8 -> 910639.88 | K17: =+B17-H17-J17 -> #REF!
B18: =SUM(B12:B17) -> #REF! | C18: =SUM(C12:C17) -> 3217473 | D18: =SUM(D13:D17) -> 0 | E18: =SUM(E13:E17) -> 0 | G18: =SUM(G12:G17) -> 688506.96 | H18: =SUM(H12:H17) -> 688506.96 | I18: =SUM(I12:I17) -> 2528965.8 | J18: =SUM(J12:J17) -> 1865515.8
C19: =+B18-C18 -> #REF! | H19: =+G18-H18 -> 0 | J19: =+I18-J18 -> 663450 | K19: =SUM(K12:K17) -> #REF!
B20: SHAREHOLDERS ACCOUNTS END MARCH | D20: 63.25 | F20: END MARCH
B21: CASA LUZ | C21: =+[1]SUMMERY!$E$19 -> 99370.136 | D21: =+C21/$D$20 -> 1571.0693 | F21: BANK MTS | G21: =+'[6]BIM Bank Control Mtn'!$J$6+'[6]Petty cash '!$G$8+'[6]Pre-paid'!$G$8 -> 304534.11 | H21: =SUM(G21:G22) -> 910639.88
B22: CASA AURORA | C22: =+'[2] SUMMERY '!$F$19 -> 197931.38 | D22: =+C22/$D$20 -> 3129.3499 | F22: DOLLAR BANK | G22: =+'[6]BIM Bank Control USD'!$J$7 -> 606105.78
B23: CASA CAJU | C23: =+[3]SUMMERY!$F$19 -> 773264.78 | D23: =+C23/$D$20 -> 12225.53 | F23: CASH | G23: =+H17 -> 475192.96
B24: CASA COCO | C24: =+'[4]SUMMERY '!$F$19 -> 878066.8 | D24: =+C24/$D$20 -> 13882.479
B25: NEGU | C25: 170900 | D25: =+C25/$D$20 -> 2701.9763
C26: =SUM(C21:C25) -> 2119533.1 | D26: =SUM(D21:D25) -> 33510.405 | G26: =SUM(G21:G25) -> 1385832.8
G29: =+G26-F9 -> #REF!

Sheet  EXPENSES
A1: LANDCO BANK EXPENSES | E1: H1 | F1: H2 | H1: H3 | I1: H4
C2: BANK PAYMENTS | D2: =SUM(D8:D62) -> 954875.91
C3: CASH PAYMENTS | D3: =SUM(D63:D79) -> 213314
C4: TOTAL | D4: =SUM(D2:D3) -> 1168189.9 | F4: =+D4/4 -> 292047.48
E5: SHARED EXPENSES
A6: DATE | B6: SUPPLER | C6: DISCRIPTION | D6: TOTAL | E6: LC SALARIES & WAGES | F6: CASUAL WORKERS AND ALLOWANCE | G6: ADVANCE SALARIES INCLUDED IN TOTAL SALRIES | H6: OFFICE AND BANK CHARGES | I6: ADMIN CHARGES (BDO & ANDRISA ) | J6: GAS AND ELECTRISITY | K6: MAINTENANCE GENERAL | L6: MAINTENANCE GARDEN & POOL | M6: SMALL TOOLS | N6: EQUIPMENT | O6: MAINTENANCE VEHICLES | P6: INSURANCE & LICENSE | Q6: DIESEL AND PETROL | R6: HOUSE KEEPING | S6: MARINTINE & MUNICIPAL TAXES IPRA &TAE | T6: COMMUNITY | U6: EXPENSES LUZ | V6: EXPENSES AURORA | W6: EXPENSES CAJU | X6: EXPENSES COCO | Y6: SUSPENCE | Z6: BALANCE
C7: Bank expenses
A8: 46083 | B8: JELSON | C8: SALARIES & WAGES | D8: 5000 | G8: =+D8 -> 5000 | Z8: =SUM(E8:Y8) -> 5000 | AA8: BANK | AB8: =+D8-Z8 -> 0
A9: 46083 | B9: BANK CHARGES | C9: BANK CHARGES | D9: 7 | H9: =+D9 -> 7 | Z9: =SUM(E9:Y9) -> 7 | AA9: BANK | AB9: =+D9-Z9 -> 0
A10: 46082 | B10: BANK CHARGES | C10: Bank Charges Dollar bank | D10: 586.33 | H10: =+D10 -> 586.33 | Z10: =SUM(E10:Y10) -> 586.33 | AA10: BANK | AB10: =+D10-Z10 -> 0
A11: 46086 | B11: EMILIO ADVANCE | C11: SALARIES & WAGES | D11: 2300 | G11: =+D11 -> 2300 | Z11: =SUM(E11:Y11) -> 2300 | AA11: BANK | AB11: =+D11-Z11 -> 0
A12: 46086 | B12: BANK CHARGES | C12: BANK CHARGES | D12: 7 | H12: =+D12 -> 7 | Z12: =SUM(E12:Y12) -> 7 | AA12: BANK | AB12: =+D12-Z12 -> 0
A13: 46086 | B13: TAFY ACCOMMODATION | C13: SALES | D13: -88044 | Y13: =+D13 -> -88044 | Z13: =SUM(E13:Y13) -> -88044 | AA13: BANK | AB13: =+D13-Z13 -> 0
A14: 46086 | B14: CALDERON ADVANCE | C14: SALARIES & WAGES | D14: 1500 | G14: =+D14 -> 1500 | Z14: =SUM(E14:Y14) -> 1500 | AA14: BANK | AB14: =+D14-Z14 -> 0
A15: 46086 | B15: BANK CHARGES | C15: BANK CHARGES | D15: 120 | H15: =+D15 -> 120 | Z15: =SUM(E15:Y15) -> 120 | AA15: BANK | AB15: =+D15-Z15 -> 0
A16: 46090 | B16: VARNISH | C16: GENERAL EXPENSES | D16: 3328 | K16: =+D16 -> 3328 | Z16: =SUM(E16:Y16) -> 3328 | AA16: BANK | AB16: =+D16-Z16 -> 0
A17: 46090 | B17: DIESEL MMR0998 | C17: MOTOR VEHICLE LANDCO | D17: 7384.37 | Q17: =+D17 -> 7384.37 | Z17: =SUM(E17:Y17) -> 7384.37 | AA17: BANK | AB17: =+D17-Z17 -> 0
A18: 46090 | B18: TOILET PAPER | C18: HOUSE KEEPING | D18: 5245 | R18: =+D18 -> 5245 | Z18: =SUM(E18:Y18) -> 5245 | AA18: BANK | AB18: =+D18-Z18 -> 0
A19: 46090 | B19: BANK CHARGES | C19: BANK CHARGES SINDICATO BEB | D19: 7 | H19: =+D19 -> 7 | Z19: =SUM(E19:Y19) -> 7 | AA19: BANK | AB19: =+D19-Z19 -> 0
A20: 46092 | B20: ELECTRICITY | C20: GAS & ELECTRISITY | D20: 51111.88 | J20: =+D20 -> 51111.88 | Z20: =SUM(E20:Y20) -> 51111.88 | AA20: BANK | AB20: =+D20-Z20 -> 0
A21: 46092 | B21: BANK CHARGES | C21: BANK CHARGES | D21: 7 | H21: =+D21 -> 7 | Z21: =SUM(E21:Y21) -> 7 | AA21: BANK | AB21: =+D21-Z21 -> 0
A22: 46092 | B22: IRPS | C22: IRPS DIFFERENCE | D22: 129.49 | G22: =+D22 -> 129.49 | Z22: =SUM(E22:Y22) -> 129.49 | AA22: BANK | AB22: =+D22-Z22 -> 0
A23: 46097 | B23: CHLOOR | C23: SWIMMING POOL CHEMICALS | D23: 8710 | L23: =+D23 -> 8710 | Z23: =SUM(E23:Y23) -> 8710 | AA23: BANK | AB23: =+D23-Z23 -> 0
A24: 46097 | B24: PLASTIC DE LUXO | C24: HOUSE KEEPING | D24: 1290 | R24: =+D24 -> 1290 | Z24: =SUM(E24:Y24) -> 1290 | AA24: BANK | AB24: =+D24-Z24 -> 0
A25: 46098 | B25: CARTO DEBITO | C25: BANK CHARGES | D25: 600 | H25: =+D25 -> 600 | Z25: =SUM(E25:Y25) -> 600 | AA25: BANK | AB25: =+D25-Z25 -> 0
A26: 46099 | B26: ACCOUNTING | C26: ADMIN AND ACCOUNTING | D26: 37386 | H26: \ | I26: =+D26 -> 37386 | Z26: =SUM(E26:Y26) -> 37386 | AA26: BANK | AB26: =+D26-Z26 -> 0
A27: 46099 | B27: BANK CHARGES | C27: BANK CHARGES | D27: 7 | H27: =+D27 -> 7 | Z27: =SUM(E27:Y27) -> 7 | AA27: BANK | AB27: =+D27-Z27 -> 0
A28: 46099 | B28: IMPRA | C28: INSURANCE JETSKI | D28: 1409.68 | P28: =+D28 -> 1409.68 | Z28: =SUM(E28:Y28) -> 1409.68 | AA28: BANK | AB28: =+D28-Z28 -> 0
A29: 46099 | B29: IMPRA | C29: INSURANCE TRAILER | D29: 1409.68 | P29: =+D29 -> 1409.68 | Z29: =SUM(E29:Y29) -> 1409.68 | AA29: BANK | AB29: =+D29-Z29 -> 0
A30: 46100 | B30: BALDE PARA CONSTRUTOR | C30: GENERAL EXPENSES | D30: 788 | K30: =+D30 -> 788 | Z30: =SUM(E30:Y30) -> 788 | AA30: BANK | AB30: =+D30-Z30 -> 0
A31: 46100 | B31: CLEANING MATERIAL | C31: HOUSE KEEPING | D31: 3330 | R31: =+D31 -> 3330 | Z31: =SUM(E31:Y31) -> 3330 | AA31: BANK | AB31: =+D31-Z31 -> 0
A32: 46100 | B32: BATTERY PRADO H4 | C32: MOTOR VEHICLES EXPENSES | D32: 10500 | X32: =+D32 -> 10500 | Z32: =SUM(E32:Y32) -> 10500 | AA32: BANK | AB32: =+D32-Z32 -> 0
A33: 46100 | B33: SEALER H3 | C33: GENERAL EXPENSES | D33: 5688 | W33: =+D33 -> 5688 | Z33: =SUM(E33:Y33) -> 5688 | AA33: BANK | AB33: =+D33-Z33 -> 0
A34: 46100 | B34: BANK CHARGES | C34: BANK CHARGES | D34: 7 | H34: =+D34 -> 7 | Z34: =SUM(E34:Y34) -> 7 | AA34: BANK | AB34: =+D34-Z34 -> 0
A35: 46105 | B35: TRANSFER DOLLARS TO METICAIS | C35: SUSPENSE | Z35: =SUM(E35:Y35) -> 0 | AA35: BANK | AB35: =+D35-Z35 -> 0
A36: 46104 | B36: PETTY CASH | C36: SUSPENSE | D36: 18889.39 | Y36: =+D36 -> 18889.39 | Z36: =SUM(E36:Y36) -> 18889.39 | AA36: BANK | AB36: =+D36-Z36 -> 0
A37: 46106 | B37: SALARY MARCH | C37: SALARIES & WAGES | D37: 305089.85 | E37: 164821 | U37: 34870.88 | V37: 58534 | W37: 36625 | X37: 43125 | Z37: =SUM(E37:Y37) -> 337975.88 | AA37: BANK | AB37: =+D37-Z37 -> -32886.03 | AC37: =+#REF! -> #REF!
A38: 46106 | B38: BANK CHARGES | C38: BANK CHARGES | D38: 257 | H38: =+D38 -> 257 | Z38: =SUM(E38:Y38) -> 257 | AA38: BANK | AB38: =+D38-Z38 -> 0
A39: 46106 | B39: ADMIN FEE | C39: ACCOUNTING AND ADMIN | D39: 146740 | I39: =+D39 -> 146740 | Z39: =SUM(E39:Y39) -> 146740 | AA39: BANK | AB39: =+D39-Z39 -> 0
A40: 46106 | B40: ACCOMMODATION ADVANCE APRIL | C40: SALES | Z40: =SUM(E40:Y40) -> 0 | AA40: BANK | AB40: =+D40-Z40 -> 0
A41: 46107 | B41: LIGHTS OUTSIDE | C41: GENERAL MAITENANCE | D41: 1440 | K41: =+D41 -> 1440 | Z41: =SUM(E41:Y41) -> 1440 | AA41: BANK | AB41: =+D41-Z41 -> 0
A42: 46107 | B42: SINDICATO | C42: SALARIES & WAGES | D42: 3379.76 | G42: =+D42 -> 3379.76 | Z42: =SUM(E42:Y42) -> 3379.76 | AA42: BANK | AB42: =+D42-Z42 -> 0
A43: 46108 | B43: SOAP, JAVEL | C43: HOUSE KEEPING | D43: 5430 | R43: =+D43 -> 5430 | Z43: =SUM(E43:Y43) -> 5430 | AA43: BANK | AB43: =+D43-Z43 -> 0
A44: 46108 | B44: TRANSFER DOLLARS TO METICAIS | C44: SUSPENSE | Z44: =SUM(E44:Y44) -> 0 | AA44: BANK | AB44: =+D44-Z44 -> 0
A45: 46108 | B45: IPRA 2026 | C45: LAND TAX | D45: 52850 | S45: =+D45 -> 52850 | Z45: =SUM(E45:Y45) -> 52850 | AA45: BANK | AB45: =+D45-Z45 -> 0
A46: 46108 | B46: TAE | C46: LAND TAX | D46: 10300 | S46: =+D46 -> 10300 | Z46: =SUM(E46:Y46) -> 10300 | AA46: BANK | AB46: =+D46-Z46 -> 0
A47: 46108 | B47: DIESEL GENERATOR | C47: ELECTRISITY | D47: 12280 | J47: =+D47 -> 12280 | Z47: =SUM(E47:Y47) -> 12280 | AA47: BANK | AB47: =+D47-Z47 -> 0
A48: 46108 | B48: Q20 OIL ANTI RUST | C48: GENERAL MAINTRENANCE | D48: 1160 | K48: =+D48 -> 1160 | Z48: =SUM(E48:Y48) -> 1160 | AA48: BANK | AB48: =+D48-Z48 -> 0
A49: 46111 | B49: DIESEL TOYOTA AKL491MP | C49: MOTOR VEHICLES EXPENSES | D49: 5385.02 | Q49: =+D49 -> 5385.02 | Z49: =SUM(E49:Y49) -> 5385.02 | AA49: BANK | AB49: =+D49-Z49 -> 0
A50: 46108 | B50: DIESEL PRADO HOUSE 4 | C50: MOTOR VEHICLES EXPENSES | D50: 3292.74 | X50: =+D50 -> 3292.74 | Z50: =SUM(E50:Y50) -> 3292.74 | AA50: BANK | AB50: =+D50-Z50 -> 0
A51: 46111 | B51: INSS | C51: SALARIES & WAGES | D51: 23658.31 | E51: =+E37*0.04-0.01 -> 6592.83 | G51: =10139.28 -> 10139.28 | U51: =+U37*0.04 -> 1394.8352 | V51: =+V37*0.04 -> 2341.36 | W51: =+W37*0.04 -> 1465 | X51: =+X37*0.04 -> 1725 | Z51: =SUM(E51:Y51) -> 23658.305 | AA51: BANK | AB51: =+D51-Z51 -> 0.0048
A52: 46111 | B52: TRANSFER DOLLARS TO METICAIS | C52: SUSPENSE | Z52: =SUM(E52:Y52) -> 0 | AA52: BANK | AB52: =+D52-Z52 -> 0
A53: 46111 | B53: INSURANCE VEHICLES | C53: INSURANCE | D53: 239672.71 | P53: =44238.15+110329.2+2572.46+0.01 -> 157139.82 | V53: 2572.46 | W53: 4630.43 | X53: 75330 | Z53: =SUM(E53:Y53) -> 239672.71 | AA53: BANK | AB53: =+D53-Z53 -> 0
A54: 46111 | B54: INSURANCE VEHICLES | C54: PUBLIC LIABILITY | D54: 37500 | P54: =+D54 -> 37500 | Z54: =SUM(E54:Y54) -> 37500 | AA54: BANK | AB54: =+D54-Z54 -> 0
A55: 46111 | B55: BANK CHARGES | C55: BANK CHARGES | D55: 120 | H55: =+D57 -> 120 | Z55: =SUM(E55:Y55) -> 120 | AA55: BANK | AB55: =+D55-Z55 -> 0
A56: 46111 | B56: WORKMENS COMPENSATIO | C56: INSURANCE | D56: 30417.98 | P56: =+D56 -> 30417.98 | Z56: =SUM(E56:Y56) -> 30417.98 | AA56: BANK | AB56: =+D56-Z56 -> 0
A57: 46111 | B57: BANK CHARGES | C57: BANK CHARGES | D57: 120 | H57: =+D57 -> 120 | Z57: =SUM(E57:Y57) -> 120 | AA57: BANK | AB57: =+D57-Z57 -> 0
A58: 46112 | B58: GAS FEBRUARY | C58: GAS & ELECTRISITY | D58: 3800.61 | J58: =+D58 -> 3800.61 | Z58: =SUM(E58:Y58) -> 3800.61 | AA58: BANK | AB58: =+D58-Z58 -> 0
A59: 46112 | B59: GLOBES | C59: GENERAL MAINTRENANCE | D59: 1235 | K59: =+D59 -> 1235 | Z59: =SUM(E59:Y59) -> 1235 | AA59: BANK | AB59: =+D59-Z59 -> 0
A60: 46112 | B60: IRPS | C60: SALARIES & WAGES | D60: 10437.5 | G60: =+D60 -> 10437.5 | Z60: =SUM(E60:Y60) -> 10437.5 | AA60: BANK | AB60: =+D60-Z60 -> 0
A61: 46083 | C61: PORTADOR MAPUTO | D61: 495 | H61: =+D61 -> 495
A62: 46084 | C62: PETTY CASH CHEQUE | D62: =-D36 -> -18889.39 | Y62: =-D62 -> 18889.39 | AA62: BANK
A63: 46085 | C63: STARLINK FOR FEB | D63: 3000 | H63: =+D63 -> 3000 | Z63: =SUM(E63:Y63) -> 3000 | AA63: CASH | AB63: =+D63-Z63 -> 0
A64: 46086 | C64: COLLECT BUDGIE AT AIRPORT 25 FEB | D64: 500 | F64: =+D64 -> 500 | Z64: =SUM(E64:Y64) -> 500 | AA64: CASH | AB64: =+D64-Z64 -> 0
A65: 46087 | C65: DEPOSIT IN0095 | D65: 88044 | Y65: =+D65 -> 88044 | Z65: =SUM(E65:Y65) -> 88044 | AA65: CASH | AB65: =+D65-Z65 -> 0
A66: 46088 | C66: PETTY CASH | D66: 5000 | R66: 2000 | V66: 1500 | W66: 1500 | Z66: =SUM(E66:Y66) -> 5000 | AA66: CASH | AB66: =+D66-Z66 -> 0
A67: 46089 | C67: HANDY ANDY, SUNLIGHT DOVE SOAP GUEST | D67: =380+340 -> 720 | R67: =+D67 -> 720 | Z67: =SUM(E67:Y67) -> 720 | AA67: CASH | AB67: =+D67-Z67 -> 0
A68: 46090 | C68: FIX INTERNET OF CASA CAJU | D68: 5000 | W68: =+D68 -> 5000 | Z68: =SUM(E68:Y68) -> 5000 | AA68: CASH | AB68: =+D68-Z68 -> 0
A69: 46091 | C69: Geraldo rubish Landco | D69: 2500 | R69: =+D69 -> 2500 | Z69: =SUM(E69:Y69) -> 2500 | AA69: CASH | AB69: =+D69-Z69 -> 0
A70: 46092 | C70: 2 X ROAD CERTIFICATES @ 3000 EACH | D70: =2*3000 -> 6000 | S70: =+D70 -> 6000 | Z70: =SUM(E70:Y70) -> 6000 | AA70: CASH | AB70: =+D70-Z70 -> 0
A71: 46093 | C71: 2 X ROAD CERTIFICATES @ 3000 EACH | D71: 6000 | W71: 3000 | X71: 3000 | Z71: =SUM(E71:Y71) -> 6000 | AA71: CASH | AB71: =+D71-Z71 -> 0
A72: 46094 | C72: FOOD WORKERS | D72: 21000 | F72: =+D72 -> 21000 | Z72: =SUM(E72:Y72) -> 21000 | AA72: CASH | AB72: =+D72-Z72 -> 0
A73: 46095 | C73: CASUALS GARDEN ABLUTION PLUS PLANTS | D73: 1800 | F73: =+D73 -> 1800 | Z73: =SUM(E73:Y73) -> 1800 | AA73: CASH | AB73: =+D73-Z73 -> 0
A74: 46096 | C74: PAVERS ABLUTION BLOCK | D74: 1200 | K74: =+D74 -> 1200 | Z74: =SUM(E74:Y74) -> 1200 | AA74: CASH | AB74: =+D74-Z74 -> 0
A75: 46097 | C75: INSPECTION FEE MARINTINE BOATS | D75: 3600 | V75: 3600 | Z75: =SUM(E75:Y75) -> 3600 | AA75: CASH | AB75: =+D75-Z75 -> 0
A76: 46098 | C76: ITRANSMAR LICENSE ROCKSTEADY | D76: =11550+400 -> 11950 | V76: =+D76 -> 11950 | Z76: =SUM(E76:Y76) -> 11950 | AA76: CASH | AB76: =+D76-Z76 -> 0
A77: 46099 | C77: PETROL ALLOWANCE | D77: 5000 | Q77: =+D77 -> 5000 | Z77: =SUM(E77:Y77) -> 5000 | AA77: CASH | AB77: =+D77-Z77 -> 0
A78: 46100 | C78: SALARY MARCH | D78: 35000 | E78: =+D78 -> 35000 | Z78: =SUM(E78:Y78) -> 35000 | AA78: CASH | AB78: =+D78-Z78 -> 0
A79: 46101 | C79: WARREN COHEN BOUGHT 4 TABLES 4 DUSTBINS | D79: =250*68 -> 17000 | X79: =+D79 -> 17000 | Z79: =SUM(E79:Y79) -> 17000 | AA79: CASH | AB79: =+D79-Z79 -> 0

Sheet  EXPENSES HOUSE
A1: LANDCO BANK EXPENSES PER HOUSE
D2: HOUSE EXPENSES
C3: SHARED | D3: SALARIES | E3: INSURANCE | F3: BOAT SKIPPERS CLEANING | G3: MAINTENANCE FIX WIFI | H3: BOAT LICENSE | I3: SEALER | J3: TABELS AND DUSTBIN | K3: PETROL & BATTERY | L3: TOTAL PERSONAL | M3: TOTAL | N3: SHARED EXPENSES | P3: SHARED
B4: CASA LUZ | C4: =SUM(P4:P20) -> 209886.3 | D4: =+' EXPENSES'!#REF! -> #REF! | L4: =SUM(D4:K4) -> #REF! | M4: =+C4+L4 -> #REF! | N4: SALARIES & WAGES | O4: 206413.83 | P4: =+O4/4 -> 51603.457
B5: CASA AURORA | C5: =+C4 -> 209886.3 | D5: =+' EXPENSES'!V51+' EXPENSES'!V37 -> 60875.36 | E5: =+' EXPENSES'!V53 -> 2572.46 | F5: 1500 | H5: =+' EXPENSES'!V75+' EXPENSES'!V76 -> 15550 | L5: =SUM(D5:K5) -> 80497.82 | M5: =+C5+L5 -> 290384.12 | N5: CASUAL WORKERS AND FOOD ALLOWANCE | O5: 23300 | P5: =+O5/4 -> 5825
B6: CASA CAJU | C6: =+C5 -> 209886.3 | D6: =+' EXPENSES'!W51+' EXPENSES'!W37 -> 38090 | E6: =+' EXPENSES'!W53+3000 -> 7630.43 | F6: 1500 | G6: 5000 | I6: =+' EXPENSES'!W33 -> 5688 | L6: =SUM(D6:K6) -> 57908.43 | M6: =+C6+L6 -> 267794.73 | N6: OFFICE AND BANK CHARGES | O6: 5340.33 | P6: =+O6/4 -> 1335.0825
B7: CASA COCO | C7: =+C6 -> 209886.3 | D7: =+' EXPENSES'!X37+' EXPENSES'!X51 -> 44850 | E7: =+' EXPENSES'!X53+3000 -> 78330 | J7: 17000 | K7: =+' EXPENSES'!X50+' EXPENSES'!X32 -> 13792.74 | L7: =SUM(D7:K7) -> 153972.74 | M7: =+C7+L7 -> 363859.04 | N7: ADMIN CHARGES (BDO & ANDRISA ENS ) | O7: 184126 | P7: =+O7/4 -> 46031.5
M8: =SUM(M4:M7) -> #REF! | N8: GAS AND ELECTRISITY | O8: 67192.49 | P8: =+O8/4 -> 16798.122
M9: =+' EXPENSES'!D4 -> 1168189.9 | N9: MAINTENANCE GENERAL | O9: 9151 | P9: =+O9/4 -> 2287.75
M10: =+M8-M9 -> #REF! | N10: MAINTENANCE GARDEN & POOL | O10: 8710 | P10: =+O10/4 -> 2177.5
N11: SMALL TOOLS | O11: 0 | P11: =+O11/4 -> 0
N12: EQUIPMENT PRESSURE PUMP X 2 | O12: 0 | P12: =+O12/4 -> 0
N13: MAINTENANCE VEHICLES | O13: 0 | P13: =+O13/4 -> 0
N14: INSURANCE & LICENSE VEHICLES | O14: 159959.18 | P14: =+O14/4 -> 39989.795
N15: INSURANCE PUBLIC LIBILITY | O15: 37500 | P15: =+O15/4 -> 9375
N16: WORKMENS COMPENSATION | O16: 30417.98 | P16: =+O16/4 -> 7604.495
N17: DIESEL AND PETROL | O17: 17769.39 | P17: =+O17/4 -> 4442.3475
N18: HOUSE KEEPING | O18: 20515 | P18: =+O18/4 -> 5128.75
N19: MARINTINE & MUNICIPAL TAXES IPRA &TAE | O19: 69150 | P19: =+O19/4 -> 17287.5
N20: COMMUNITY DONATION | O20: 0 | P20: =+O20/4 -> 0
N24: EXPENSES LUZ | O24: 36265.715 | P24: =+O24 -> 36265.715
N25: EXPENSES AURORA | O25: 80497.82 | P25: =+O25 -> 80497.82
N26: EXPENSES CAJU | O26: 57908.43 | P26: =+O26 -> 57908.43
N27: EXPENSES COCO | O27: 153972.74 | P27: =+O27 -> 153972.74
N29: SHARED EXPENSES | P29: =SUM(P4:P19) -> 209886.3
N30: HOUSE EXPENSES | O30: =+' EXPENSES'!#REF! -> #REF! | P30: =SUM(P24:P27) -> 328644.71
O31: =+O28-O30 -> #REF!

Sheet MONTHLY FOR THE YEAR
A1: LANDCO EXPENSES
B2: MONTH | C2: EXPENSES | D2: 63.25
B4: 46023 | C4: =+' EXPENSES'!#REF! -> #REF! | D4: =+C4/$D$2 -> #REF!
B5: 46055 | D5: =+C5/$D$2 -> 0
B6: 46087 | D6: =+C6/$D$2 -> 0
B7: 46119 | D7: =+C7/$D$2 -> 0
B8: 46151 | D8: =+C8/$D$2 -> 0
B9: 46183 | D9: =+C9/$D$2 -> 0
B10: 46215 | D10: =+C10/$D$2 -> 0
B11: 46247 | D11: =+C11/$D$2 -> 0
B12: 46279 | D12: =+C12/$D$2 -> 0
B13: 46311 | D13: =+C13/$D$2 -> 0
B14: 46343 | D14: =+C14/$D$2 -> 0
B15: 46375 | D15: =+C15/$D$2 -> 0
C16: =SUM(C4:C15) -> #REF! | D16: =SUM(D4:D15) -> #REF!
B18: AVERAGE | C18: =+C16/9 -> #REF! | D18: =+D16/9 -> #REF!
