Workbook

Sheet INCOME
A1: LANDCO INCOME | D1: H1 | E1: =+E49 -> 1936650 | F1: =+E1/63.25 -> 30618.972
D2: H2 | E2: =+F49 -> 4051090 | F2: =+E2/63.25 -> 64048.854
D3: H3 | E3: =+G49 -> 4999448 | F3: =+E3/63.25 -> 79042.656
D4: H4 | E4: =+H49 -> 3084132 | F4: =+E4/63.25 -> 48760.98
E5: =SUM(E1:E4) -> 14071320 | F5: =+E5/63.25 -> 222471.46 | G5: =SUM(F1:F4) -> 222471.46
A6: DATE | B6: HOUSE | C6: NAME | D6: ACCOMODATION | E6: H1 | F6: H2 | G6: H3 | H6: H4 | I6: TOTAL MTS | J6: DOLLARS | K6: TOTAL PER MONTH
A7: 45659 | B7: 3 | C7: ALEX | D7: 594297 | E7: 0 | G7: =+D7 -> 594297 | I7: =SUM(E7:H7) -> 594297 | J7: =+D7/63.25 -> 9396 | K7: =SUM(I7:I9) -> 1846127
A8: 45673 | B8: 2 | C8: WARREN STEAD | D8: 958350 | F8: =+D8 -> 958350 | I8: =SUM(E8:H8) -> 958350 | J8: =+D8/63.25 -> 15151.779
A9: 45681 | B9: 3 | C9: ALEX | D9: 293480 | G9: =+D9 -> 293480 | I9: =SUM(E9:H9) -> 293480 | J9: =+D9/63.25 -> 4640
A11: 45713 | B11: 3 | C11: CREDIT IVA H3 - KEITH & SUE X 8 NIGHTS @ 75 | D11: 40200 | G11: =+D11 -> 40200 | I11: =+D11 -> 40200 | J11: =+D11/67 -> 600 | K11: =+I11 -> 40200
A13: 45720 | B13: 3 | C13: ALEX | D13: 751171 | G13: =+D13 -> 751171 | I13: =SUM(E13:H13) -> 751171 | J13: =+D13/63.25 -> 11876.221 | K13: =SUM(D13:D16) -> 2299693
A14: 45740 | B14: 4 | C14: WARREN PAY TRACY SALARY AND RECRUITMENT | D14: =6942*66 -> 458172 | H14: =+D14 -> 458172 | I14: =SUM(E14:H14) -> 458172 | J14: =+D14/66 -> 6942
A15: 45741 | B15: 2 | C15: WARREN STEAD | D15: 958350 | F15: =+D15 -> 958350 | I15: =SUM(E15:H15) -> 958350 | J15: =+D15/63.25 -> 15151.779
A16: 45741 | B16: 3 | C16: ALEX | D16: =2000*66 -> 132000 | G16: =+D16 -> 132000 | I16: =SUM(E16:H16) -> 132000 | J16: =+D16/66 -> 2000
A18: 45763 | B18: 1 | C18: TAFY RECEIVED FROM ROBIN | D18: =6950*67 -> 465650 | E18: =+D18 -> 465650 | J18: 6950 | K18: =SUM(D18:D20) -> 923170
A19: 45763 | B19: 2 | C19: BRENDON 7 DAYS @80 | D19: =560*67 -> 37520 | F19: =+D19 -> 37520 | J19: =7*80 -> 560
A20: 45777 | B20: 3 | C20: KEIVIN PAY TO BANK | D20: =+'[1]Breakdown of Income'!$C$9 -> 420000 | G20: =+D20 -> 420000 | J20: =+G20/63.25 -> 6640.3162
A22: 45800 | B22: 1 | C22: TAFY RECEIVED FROM AANGIE | D22: =5000*62 -> 310000 | E22: =+D22 -> 310000 | J22: 5000 | K22: =SUM(D22:D24) -> 1268350
A24: 45811 | B24: 1 | C24: ALEX | D24: 958350 | G24: =+D24 -> 958350 | J24: =+D24/63.25 -> 15151.779 | K24: =SUM(D24:D26) -> 2865450
A25: 45828 | B25: 4 | C25: WARREN COHEN INVESTMENT | D25: =15000*63.25 -> 948750 | H25: =+D25 -> 948750 | J25: =+D25/63.25 -> 15000
A26: 45829 | B26: 3 | C26: WARREN STEAD | D26: 958350 | F26: =+D26 -> 958350 | J26: =+D26/63.25 -> 15151.779
A28: 45854 | B28: 1 | C28: TAFY RECEIVED FROM ALEX | D28: =+J28*67 -> 335000 | E28: =+D28 -> 335000 | J28: 5000 | K28: =SUM(D28:D290) -> 7547805
A29: 45855 | B29: 4 | C29: ARON ACCOMMODATION IN H4 | D29: =1470*67 -> 98490 | H29: =+D29 -> 98490 | J29: 1470
A31: 45880 | B31: 1 | C31: CREDIT IVA H1 - LESLEY X 6 NIGHTS | D31: =+J31*68 -> 68000 | E31: =+D31 -> 68000 | J31: 1000 | K31: =SUM(D31:D293) -> 7114315
A32: 45894 | B32: 2 | C32: WARREN | D32: =+J32*68 -> 119000 | F32: =+D32 -> 119000 | J32: =1250+500 -> 1750
A34: 45912 | B34: 3 | C34: ALEX | D34: 638900 | G34: =+D34 -> 638900 | I34: =SUM(E34:H34) -> 638900 | J34: =+D34/63.25 -> 10101.186 | K34: =SUM(D34:D37) -> 1641540
A35: 45922 | B35: 4 | C35: ALAIN WARREN | D35: 60720 | H35: =+D35 -> 60720 | J35: =+D35/69 -> 880
A37: 45940 | B37: 2 | C37: WARREN STEAD | D37: =617120+324800 -> 941920 | F37: =+D37 -> 941920 | J37: =+D37/63.25 -> 14892.016 | K37: =SUM(D37:D39) -> 2112970
A38: 45953 | B38: 3 | C38: ALEX TRANSFER TO MONIQUE | D38: 222300 | G38: =57000*3.9 -> 222300 | J38: 3000
A39: 45954 | B39: 4 | C39: WARREN COHEN INVESTMENT | D39: =15000*63.25 -> 948750 | H39: =15000*63.25 -> 948750 | J39: =+H39/63.25 -> 15000
A41: 45979 | B41: 3 | C41: ALEX | D41: 948750 | G41: =+D41 -> 948750 | J41: =+D41/63.25 -> 15000 | K41: =SUM(D41:D44) -> 1522150
A42: 45980 | B42: 2 | C42: BRENDON | D42: =320*70 -> 22400 | F42: =+D42 -> 22400 | J42: 320
A43: 45986 | B43: 1 | C43: TAFY | D43: =551000 -> 551000 | E43: =+D43 -> 551000 | J43: =+D43/63.25 -> 8711.4625
A45: 46007 | B45: 2 | C45: BRENDON | D45: =800*69 -> 55200 | F45: =+D45 -> 55200 | J45: 800
A46: 46020 | B46: 1 | C46: TAFY RE ROBIN | D46: =3000*69 -> 207000 | E46: =+D46 -> 207000 | J46: 3000
A47: 46020 | B47: 3 | C47: REVERSE ALEX TRANSFER TO ALEX ENVELOPE | G47: =+D47 -> 0
A48: 46020 | B48: 4 | C48: WARREN INVESTMENT DOLLAR ACCOUNT | D48: =9000*63.25 -> 569250 | H48: =+D48 -> 569250 | J48: 9000
E49: =SUM(E7:E48) -> 1936650 | F49: =SUM(F7:F48) -> 4051090 | G49: =SUM(G7:G48) -> 4999448 | H49: =SUM(H7:H48) -> 3084132 | I49: =SUM(I7:I48) -> 4824920 | J49: =SUM(J7:J48) -> 220136.32 | K49: =SUM(D50:D51) -> 1761125
A50: 46031 | B50: 2 | C50: WARREN STEAD DEP BANK | D50: =SUM('[2]BIM Bank Control Mtn'!$G$15:$G$17) -> 948750 | F50: =+D50 -> 948750 | J50: =+D50/63.25 -> 15000
A51: 46038 | B51: 1 | C51: TAFY | D51: =+J51*67 -> 812375 | E51: =+D51 -> 812375 | J51: =+'[3]LANDCO US$ CASH'!$E$20 -> 12125

Sheet RECON
D1: 46023
C3: BALANCE END DEC | D3: INCOME JAN | E3: EXPENSES JAN | F3: TOTAL END JAN
B4: CASA LUZ | C4: =+[4]RECON!$F$4 -> -456526.24 | D4: =+INCOME!E51 -> 812375 | E4: =+' EXPENSES HOUSE'!L4 -> 183410.17 | F4: =+C4+D4-E4 -> 172438.58 | H4: =+F4-C21 -> 0
B5: CASA AURORA | C5: =+[4]RECON!$F$5 -> -9572.7775 | D5: =+INCOME!F50 -> 948750 | E5: =+' EXPENSES HOUSE'!L5 -> 211718.57 | F5: =+C5+D5-E5 -> 727458.65 | H5: =+F5-C22 -> -0.0024999999
B6: CASA CAJU | C6: =+[4]RECON!$F$6 -> 724450.72 | D6: =+INCOME!G47 -> 0 | E6: =+' EXPENSES HOUSE'!L6 -> 196921.21 | F6: =+C6+D6-E6 -> 527529.51 | H6: =+F6-C23 -> 0
B7: CASA COCO | C7: =+[4]RECON!$F$7 -> 345627.78 | E7: =+' EXPENSES HOUSE'!L7 -> 193473.21 | F7: =+C7+D7-E7 -> 152154.57 | H7: =+F7-C24 -> 0
B8: NEGU | C8: 170900 | E8: 0 | F8: =+C8+D8-E8 -> 170900
B9: Total | C9: =SUM(C4:C8) -> 774879.48 | D9: =SUM(D4:D8) -> 1761125 | E9: =SUM(E4:E8) -> 785523.17 | F9: =SUM(F4:F8) -> 1750481.3
B11: SHAREHOLDERS | D11: ADD INCOME | G11: PETTY CASH | I11: BANK/PRE-PAID & $
C12: =+[4]RECON!$B$17 -> 774879.48 | F12: OPEN BALANCE | G12: =+'[3]LANDCO MET CASH'!$F$5 -> -143050.54 | I12: 917929.78 | K12: =+C12-G12-I12 -> 0.2408
C13: =+D9 -> 1761125 | F13: INCOME | G13: =+'[3]LANDCO MET CASH'!$F$6 -> 812375 | I13: =SUM('[2]BIM Bank Control Mtn'!$G$15:$G$17) -> 948750 | K13: =+C13-G13-I13 -> 0
F14: ADD INCOME | K14: =+C14-G14-I14 -> 0
K15: =+C15-G15-I15 -> 0
B16: =+E9 -> 785523.17 | F16: PAYMENTS | H16: =+'[3]LANDCO MET CASH'!$F$8 -> 111660 | J16: =+'[2]BIM Bank Control Mtn'!$L$5+'[2]Petty cash '!$G$7+'[2]Pre-paid'!$G$7-10088 -> 673863.17 | K16: =+B16-H16-J16 -> 0
B17: =+F9 -> 1750481.3 | F17: BALANCE | H17: =+'[3]LANDCO MET CASH'!$F$9 -> 557664.46 | J17: =+'[2]BIM Bank Control USD'!$I$7+'[2]BIM Bank Control Mtn'!$J$6+'[2]Petty cash '!$G$8+'[2]Pre-paid'!$G$8-3464.73 -> 1192816.6 | K17: =+B17-H17-J17 -> 0.2383
B18: =SUM(B12:B17) -> 2536004.5 | C18: =SUM(C12:C17) -> 2536004.5 | D18: =SUM(D13:D17) -> 0 | E18: =SUM(E13:E17) -> 0 | G18: =SUM(G12:G17) -> 669324.46 | H18: =SUM(H12:H17) -> 669324.46 | I18: =SUM(I12:I17) -> 1866679.8 | J18: =SUM(J12:J17) -> 1866679.8
C19: =+B18-C18 -> 0 | H19: =+G18-H18 -> 0 | J19: =+I18-J18 -> -0.0024999999 | K19: =SUM(K12:K17) -> 0.4791
B20: SHAREHOLDERS ACCOUNTS END JAN | D20: 63.25 | F20: END JAN
B21: CASA LUZ | C21: =+[5]SUMMERY!$E$19 -> 172438.58 | D21: =+C21/$D$20 -> 2726.3017 | F21: BANK | G21: =+'[2]BIM Bank Control Mtn'!$J$6+'[2]Petty cash '!$G$8+'[2]Pre-paid'!$G$8-3464.49 -> 775874.75 | I21: RECEIVED TO REPLAY BURGARY
B22: CASA AURORA | C22: =+'[6] SUMMERY '!$F$19 -> 727458.65 | D22: =+C22/$D$20 -> 11501.323 | F22: CASH | G22: =+'[3]LANDCO MET CASH'!$F$9 -> 557664.46 | I22: WARREN STEAD | J22: =1375 -> 1375 | K22: =+J22*70 -> 96250
B23: CASA CAJU | C23: =+[7]SUMMERY!$F$19 -> 527529.51 | D23: =+C23/$D$20 -> 8340.3875 | F23: DOLLAR BANK | G23: =+'[2]BIM Bank Control USD'!$I$7 -> 416942.1 | I23: TAFY | J23: 1375 | K23: =+J23*70 -> 96250 | L23: received Jan
B24: CASA COCO | C24: =+'[8]SUMMERY '!$F$19 -> 152154.57 | D24: =+C24/$D$20 -> 2405.6058 | I24: ALEX | J24: 0 | K24: =+J24*69 -> 0
B25: NEGO | C25: 170900 | D25: =+C25/$D$20 -> 2701.9763 | I25: WARREN COHEN | J25: 0
C26: =SUM(C21:C25) -> 1750481.3 | D26: =SUM(D21:D25) -> 27675.594 | G26: =SUM(G21:G25) -> 1750481.3
I27: RECEIVED IN METS | K27: =SUM(K22:K25) -> 192500
I28: PETTY CASH | K28: -140925.9
G29: =+G26-F9 -> 0.0016999997 | I29: ANDRISA CASH | K29: -70000
I30: NEGU | K30: -170900
J31: =SUM(J22:J30) -> 2750 | K31: =SUM(K27:K30) -> -189325.9

Sheet  EXPENSES
A1: LANDCO BANK EXPENSES | F1: H1 | G1: H2 | I1: H3 | J1: H4
C2: BANK PAYMENTS | E2: =SUM(E8:E82) -> 683863.17
C3: CASH PAYMENTS | E3: =SUM(E84:E103) -> 101660 | W3: =+#REF!-E2 -> #REF!
C4: TOTAL | E4: =SUM(E2:E3) -> 785523.17 | G4: =+E4/4 -> 196380.79 | H4: =+G4/63.25 -> 3104.8347
F5: SHARED EXPENSES
A6: DATE | B6: SUPPLER | C6: DISCRIPTION | E6: TOTAL | F6: LC SALARIES & WAGES | G6: CASUAL WORKERS AND ALLOWANCE | H6: ADVANCE SALARIES INCLUDED IN TOTAL SALRIES | I6: OFFICE AND BANK CHARGES | J6: ADMIN CHARGES (BDO & ANDRISA ) | K6: GAS AND ELECTRISITY | L6: MAINTENANCE GENERAL | M6: MAINTENANCE GARDEN & POOL | N6: SMALL TOOLS | O6: EQUIPMENT | P6: MAINTENANCE VEHICLES | Q6: INSURANCE & LICENSE | R6: DIESEL AND PETROL | S6: HOUSE KEEPING | T6: MARINTINE & MUNICIPAL TAXES IPRA &TAE | U6: COMMUNITY | V6: EXPENSES LUZ | W6: EXPENSES AURORA | X6: EXPENSES CAJU | Y6: EXPENSES COCO | Z6: SUSPENCE | AA6: BALANCE
C7: Bank expenses
A8: 46025 | B8: ENH DECEMBER | C8: GAS DECEMBER | E8: 6426.95 | K8: =+E8 -> 6426.95 | AA8: =SUM(F8:Z8) -> 6426.95 | AB8: BANK | AC8: =+E8-AA8 -> 0
A9: 46025 | B9: TRANSFER FROM DOLLAR ACCOUNT | C9: SUSPENSE | AA9: =SUM(F9:Z9) -> 0 | AB9: BANK | AC9: =+E9-AA9 -> 0
A10: 46028 | B10: PAINT STEEL | C10: GENERAL MAINENANCE | E10: 1420.24 | L10: =+E10 -> 1420.24 | AA10: =SUM(F10:Z10) -> 1420.24 | AB10: BANK | AC10: =+E10-AA10 -> 0
A11: 46031 | B11: WARREN STEAD | C11: DEBTORS | AA11: =SUM(F11:Z11) -> 0 | AB11: BANK | AC11: =+E11-AA11 -> 0
A12: 46031 | B12: WARREN STEAD | C12: SALES | AA12: =SUM(F12:Z12) -> 0 | AB12: BANK | AC12: =+E12-AA12 -> 0
A13: 46031 | B13: WARREN STEAD | C13: DEBTORS | AA13: =SUM(F13:Z13) -> 0 | AB13: BANK | AC13: =+E13-AA13 -> 0
A14: 46033 | B14: FELIX ADVANCE | C14: SALARIES & WAGES | E14: 2500 | H14: =+E14 -> 2500 | AA14: =SUM(F14:Z14) -> 2500 | AB14: BANK | AC14: =+E14-AA14 -> 0
A15: 46033 | B15: TRANSFER FEE | C15: BANKCHARGES OFFICE EXPENSES | E15: 7 | I15: =+E15 -> 7 | AA15: =SUM(F15:Z15) -> 7 | AB15: BANK | AC15: =+E15-AA15 -> 0
A16: 46033 | B16: ADMIN FEE | C16: ADMIN AND ACCOUNTING | E16: 146740 | J16: =+E16 -> 146740 | AA16: =SUM(F16:Z16) -> 146740 | AB16: BANK | AC16: =+E16-AA16 -> 0
A17: 46033 | B17: TRANSFER FEE | C17: BANKCHARGES OFFICE EXPENSES | E17: 7 | I17: =+E17 -> 7 | AA17: =SUM(F17:Z17) -> 7 | AB17: BANK | AC17: =+E17-AA17 -> 0
A18: 46033 | B18: ELECTRICITY DECEMBER | C18: GAS & ELECTRISITY | E18: 77851.16 | K18: =+E18 -> 77851.16 | AA18: =SUM(F18:Z18) -> 77851.16 | AB18: BANK | AC18: =+E18-AA18 -> 0
A19: 46033 | B19: TRANSFER FEE | C19: BANKCHARGES OFFICE EXPENSES | E19: 7 | I19: =+E19 -> 7 | AA19: =SUM(F19:Z19) -> 7 | AB19: BANK | AC19: =+E19-AA19 -> 0
A20: 46034 | B20: FELIX ADVANCE | C20: SALARIES $WAGES | E20: 3000 | H20: =+E20 -> 3000 | AA20: =SUM(F20:Z20) -> 3000 | AB20: BANK | AC20: =+E20-AA20 -> 0
A21: 46034 | B21: TRANSFER FEE | C21: BANKCHARGES OFFICE EXPENSES | E21: 7 | I21: =+E21 -> 7 | AA21: =SUM(F21:Z21) -> 7 | AB21: BANK | AC21: =+E21-AA21 -> 0
A22: 46038 | B22: ADVANCE JELSON | C22: SALARIES & WAGES | E22: 1500 | H22: =+E22 -> 1500 | AA22: =SUM(F22:Z22) -> 1500 | AB22: BANK | AC22: =+E22-AA22 -> 0
A23: 46038 | B23: TRANSFER FEE | C23: BANK CHARGES OFFICE EXPENSES | E23: 7 | I23: =+E23 -> 7 | AA23: =SUM(F23:Z23) -> 7 | AB23: BANK | AC23: =+E23-AA23 -> 0
A24: 46042 | B24: ACCOUNTING FEE JANUARY | C24: ACCOUNTING FEE | E24: 37385.8 | J24: =+E24 -> 37385.8 | AA24: =SUM(F24:Z24) -> 37385.8 | AB24: BANK | AC24: =+E24-AA24 -> 0
A25: 46042 | B25: TRANSFER FEE | C25: BANK CHARGES OFFICE EXPENSES | E25: 7 | I25: =+E25 -> 7 | AA25: =SUM(F25:Z25) -> 7 | AB25: BANK | AC25: =+E25-AA25 -> 0
A26: 46044 | B26: FILES | C26: STATIONARY | E26: 1500 | I26: =+E26 -> 1500 | AA26: =SUM(F26:Z26) -> 1500 | AB26: BANK | AC26: =+E26-AA26 -> 0
A27: 46044 | B27: TRANSFER FEE | C27: BANK CHARGES OFFICE EXPENSES | E27: 7 | I27: =+E27 -> 7 | AA27: =SUM(F27:Z27) -> 7 | AB27: BANK | AC27: =+E27-AA27 -> 0
A28: 46045 | B28: COTOVELO PVC | C28: GENERAL MAITENANCE | E28: 1037.39 | L28: =+E28 -> 1037.39 | AA28: =SUM(F28:Z28) -> 1037.39 | AB28: BANK | AC28: =+E28-AA28 -> 0
A29: 46044 | B29: TRANSFER TO PETTY CASH | C29: SUSPENCE | E29: 10000 | Z29: =+E29 -> 10000 | AA29: =SUM(F29:Z29) -> 10000 | AB29: BANK | AC29: =+E29-AA29 -> 0
A30: 46045 | B30: SALARIES JANUARY | C30: SALARIES & WAGES | E30: 315176.58 | F30: 174740 | V30: 33449 | W30: 58534 | X30: 36625 | Y30: 43125 | AA30: =SUM(F30:Z30) -> 346473 | AB30: BANK | AC30: =+E30-AA30 -> -31296.42 | AE30: =+AC30+AA105 -> 0
A31: 46045 | B31: BANK CHARGES | C31: OFFICE EXPENSES | E31: 257 | I31: =+E31 -> 257 | AA31: =SUM(F31:Z31) -> 257 | AB31: BANK | AC31: =+E31-AA31 -> 0
A32: 46045 | B32: BREAD | C32: WORKERS FOOD ALOWANCE | E32: 12000 | G32: =+E32 -> 12000 | AA32: =SUM(F32:Z32) -> 12000 | AB32: BANK | AC32: =+E32-AA32 -> 0
A33: 46048 | B33: IRPS | C33: SALARIES$ WAGES | E33: 10437.5 | H33: =+E33 -> 10437.5 | AA33: =SUM(F33:Z33) -> 10437.5 | AB33: BANK | AC33: =+E33-AA33 -> 0
A34: 46048 | B34: INSS | C34: SALARIES$ WAGES | E34: 24253.11 | F34: =+F30*0.04 -> 6989.6 | H34: =+'[9]Folha de salarios'!$AB$31 -> 10394.19 | V34: =+V30*0.04 -> 1337.96 | W34: =+W30*0.04 -> 2341.36 | X34: =+X30*0.04 -> 1465 | Y34: =+Y30*0.04 -> 1725 | AA34: =SUM(F34:Z34) -> 24253.11 | AB34: BANK | AC34: =+E34-AA34 -> 0
A35: 46050 | B35: DILUENTE ESMALTE QD 750ML | C35: GENERAL MAINTENANCE | E35: 524 | L35: =+E35 -> 524 | AA35: =SUM(F35:Z35) -> 524 | AB35: BANK | AC35: =+E35-AA35 -> 0
A36: 46051 | B36: GAS JANUARY | C36: GAS & ELECTRISITY | E36: 4833.15 | K36: =+E36 -> 4833.15 | AA36: =SUM(F36:Z36) -> 4833.15 | AB36: BANK | AC36: =+E36-AA36 -> 0
A37: 46051 | B37: TRANSFER FEE | C37: BANKCHARGES OFFICE EXPENSES | E37: 7 | I37: =+E37 -> 7 | AA37: =SUM(F37:Z37) -> 7 | AB37: BANK | AC37: =+E37-AA37 -> 0
A38: 46051 | B38: LESCO - CX PROVA DE AGUA 4X4 | C38: GENERAL MAINTENANCE | E38: 2025 | L38: =+E38 -> 2025 | AA38: =SUM(F38:Z38) -> 2025 | AB38: BANK | AC38: =+E38-AA38 -> 0
A39: 46051 | B39: 2 TOMADA SA E 2 CX 4X4 | C39: GENERAL MAINTENANCE | E39: 900 | L39: =+E39 -> 900 | AA39: =SUM(F39:Z39) -> 900 | AB39: BANK | AC39: =+E39-AA39 -> 0
A40: 46059 | B40: LIONEL | C40: UNION FEE | E40: =+'[9]Folha de salarios'!$AC$31 -> 3464.73 | H40: =+E40 -> 3464.73 | AA40: =SUM(F40:Z40) -> 3464.73 | AB40: BANK | AC40: =+E40-AA40 -> 0
AA41: =SUM(F41:Z41) -> 0 | AC41: =+E41-AA41 -> 0
A42: 46028 | B42: DOCUMENTS TO MAPUTO | C42: OFFICE & BANK CHARGES | E42: 575 | I42: =+E42 -> 575 | AA42: =SUM(F42:Z42) -> 575 | AB42: PETTY CAH | AC42: =+E42-AA42 -> 0
A43: 46028 | B43: BEBE | C43: PETTY CSH | E43: 10000 | L43: =+E43 -> 10000 | AA43: =SUM(F43:Z43) -> 10000 | AB43: PETTY CAH | AC43: =+E43-AA43 -> 0
A44: 46036 | B44: FINE ON LATE PY OF 2023 | C44: FINES | E44: 1462.56 | I44: =+E44 -> 1462.56 | AA44: =SUM(F44:Z44) -> 1462.56 | AB44: PETTY CAH | AC44: =+E44-AA44 -> 0
A45: 46044 | B45: TRANSFER FROM CHEQUE ACCOUNT | E45: -10000 | Z45: =+E45 -> -10000 | AA45: =SUM(F45:Z45) -> -10000 | AB45: PETTY CAH | AC45: =+E45-AA45 -> 0
A46: 46045 | B46: TRANSFER TO PRE-PAID | C46: SUSPENSE | E46: 88 | Z46: =+E46 -> 88 | AA46: =SUM(F46:Z46) -> 88 | AB46: PETTY CAH | AC46: =+E46-AA46 -> 0
AA47: =SUM(F47:Z47) -> 0 | AC47: =+E47-AA47 -> 0
A48: 46029 | B48: SAND PAPER & LUBRICATE SPRAY | C48: GENERAL MAITENANCE | E48: 8329 | L48: =+E48 -> 8329 | AA48: =SUM(F48:Z48) -> 8329 | AB48: PREPAID | AC48: =+E48-AA48 -> 0
A49: 46045 | B49: STEEL FOR SECURITY DOOR | C49: NEW BUILDING | E49: 10208 | X49: =+E49 -> 10208 | AA49: =SUM(F49:Z49) -> 10208 | AB49: PREPAID | AC49: =+E49-AA49 -> 0
A50: 46045 | B50: TRANSFER | C50: SUSPENSE | E50: -88 | Z50: =+E50 -> -88 | AA50: =SUM(F50:Z50) -> -88 | AB50: PREPAID | AC50: =+E50-AA50 -> 0
AA51: =SUM(F51:Z51) -> 0 | AB51: BANK | AC51: =+E51-AA51 -> 0
AA52: =SUM(F52:Z52) -> 0 | AB52: BANK | AC52: =+E52-AA52 -> 0
AA53: =SUM(F53:Z53) -> 0 | AB53: BANK | AC53: =+E53-AA53 -> 0
AA54: =SUM(F54:Z54) -> 0 | AB54: BANK | AC54: =+E54-AA54 -> 0
AA55: =SUM(F55:Z55) -> 0 | AB55: BANK | AC55: =+E55-AA55 -> 0
AA56: =SUM(F56:Z56) -> 0 | AB56: BANK | AC56: =+E56-AA56 -> 0
AA57: =SUM(F57:Z57) -> 0 | AB57: BANK | AC57: =+E57-AA57 -> 0
AA58: =SUM(F58:Z58) -> 0 | AB58: BANK | AC58: =+E58-AA58 -> 0
AA59: =SUM(F59:Z59) -> 0 | AB59: BANK | AC59: =+E59-AA59 -> 0
AA60: =SUM(F60:Z60) -> 0 | AB60: BANK | AC60: =+E60-AA60 -> 0
AA61: =SUM(F61:Z61) -> 0 | AB61: BANK | AC61: =+E61-AA61 -> 0
AA62: =SUM(F62:Z62) -> 0 | AB62: BANK | AC62: =+E62-AA62 -> 0
... AA76: =SUM(F76:Z76) -> 0 | AB76: BANK | AC76: =+E76-AA76 -> 0
R77: =+E77 -> 0 | AA77: =SUM(F77:Z77) -> 0 | AB77: BANK | AC77: =+E77-AA77 -> 0
AA78: =SUM(F78:Z78) -> 0 | AB78: BANK | AC78: =+E78-AA78 -> 0
AA79: =SUM(F79:Z79) -> 0 | AB79: BANK | AC79: =+E79-AA79 -> 0
AA80: =SUM(F80:Z80) -> 0 | AB80: BANK | AC80: =+E80-AA80 -> 0
AA81: =SUM(F81:Z81) -> 0 | AB81: BANK | AC81: =+E81-AA81 -> 0
AA82: =SUM(F82:Z82) -> 0 | AB82: BANK | AC82: =+E82-AA82 -> 0
AC83: =+E83-AA83 -> 0
A84: 46023 | B84: ALEX | C84: STARLINK FOR JAN | E84: 3000 | I84: =+E84 -> 3000 | AA84: =SUM(F84:Z84) -> 3000 | AB84: CASH | AC84: =+E84-AA84 -> 0
A85: 46025 | B85: EUZEBIO | C85: MONEY FOR OPERATION | E85: 3000 | U85: =+E85 -> 3000 | AA85: =SUM(F85:Z85) -> 3000 | AB85: CASH | AC85: =+E85-AA85 -> 0
A86: 46034 | B86: MATIAS | C86: CASUAL GUARD FOR JANUARY | E86: 7000 | G86: =+E86 -> 7000 | AA86: =SUM(F86:Z86) -> 7000 | AB86: CASH | AC86: =+E86-AA86 -> 0
A87: 46043 | B87: BEBE | C87: FOOD FOR WORKERS | E87: 21000 | G87: =+E87 -> 21000 | AA87: =SUM(F87:Z87) -> 21000 | AB87: CASH | AC87: =+E87-AA87 -> 0
A88: 46046 | B88: DOLLARS | C88: TRANSFER FROM DOLLAR ACCOUNT $6000 @ 67 | AA88: =SUM(F88:Z88) -> 0 | AB88: CASH | AC88: =+E88-AA88 -> 0
A89: 46052 | B89: WELDER | C89: RAYMONDO FOR ACCOMMODATION 9 DAY @1500 | E89: 9000 | G89: =+E89 -> 9000 | AA89: =SUM(F89:Z89) -> 9000 | AB89: CASH | AC89: =+E89-AA89 -> 0
A90: 46053 | B90: CHRIS | C90: CHRIS MONTHLY JANUARY | E90: =500*70 -> 35000 | F90: =+E90 -> 35000 | AA90: =SUM(F90:Z90) -> 35000 | AB90: CASH | AC90: =+E90-AA90 -> 0
A91: 46053 | B91: WARREN | C91: =+'[3]LANDCO MET CASH'!$C$23 -> Shortfall on Ronny money from Warren | E91: =+'[3]LANDCO MET CASH'!$F$23 -> 2220 | W91: =+E91 -> 2220 | AA91: =SUM(F91:Z91) -> 2220 | AB91: CASH | AC91: =+E91-AA91 -> 0
A92: 46053 | B92: BEBE | C92: BEBE LEAVE ONE WEEK DOUG | E92: =320*67 -> 21440 | F92: =+E92 -> 21440 | AA92: =SUM(F92:Z92) -> 21440 | AB92: CASH | AC92: =+E92-AA92 -> 0
AA93: =SUM(F93:Z93) -> 0 | AB93: CASH | AC93: =+E93-AA93 -> 0
AA94: =SUM(F94:Z94) -> 0 | AB94: CASH | AC94: =+E94-AA94 -> 0
AA95: =SUM(F95:Z95) -> 0 | AB95: CASH | AC95: =+E95-AA95 -> 0
AA96: =SUM(F96:Z96) -> 0 | AB96: CASH | AC96: =+E96-AA96 -> 0
AA97: =SUM(F97:Z97) -> 0 | AB97: CASH
AA98: =SUM(F98:Z98) -> 0 | AB98: CASH
AA99: =SUM(F99:Z99) -> 0 | AB99: CASH
AA100: =SUM(F100:Z100) -> 0 | AB100: CASH
AA101: =SUM(F101:Z101) -> 0 | AB101: CASH
AA102: =SUM(F102:Z102) -> 0 | AB102: CASH
AA103: =SUM(F103:Z103) -> 0 | AB103: CASH
C104: TOTAL | E104: =SUM(E8:E103) -> 785523.17 | F104: =SUM(F8:F103) -> 238169.6 | G104: =SUM(G8:G103) -> 49000 | H104: =SUM(H8:H103) -> 31296.42 | I104: =SUM(I8:I103) -> 6850.56 | J104: =SUM(J8:J103) -> 184125.8 | K104: =SUM(K8:K103) -> 89111.26 | L104: =SUM(L8:L103) -> 24235.63 | ... W104: =SUM(W8:W103) -> 63095.36 | X104: =SUM(X7:X103) -> 48298 | Y104: =SUM(Y8:Y103) -> 44850 | Z104: =SUM(Z8:Z103) -> 0 | AA104: =SUM(AA8:AA103) -> 816819.59
AA105: =+H104 -> 31296.42
AA106: =+AA104-AA105 -> 785523.17
C107: SHARED EXPENSES | AA107: =+E104-AA106 -> 0
C108: SALARIES & WAGES | E108: =+F104 -> 238169.6
C109: CASUAL WORKERS AND FOOD ALLOWANCE | E109: =+G104 -> 49000
C110: OFFICE AND BANK CHARGES | E110: =+I104 -> 6850.56
C111: ADMIN CHARGES (BDO & ANDRISA ENS ) | E111: =+J104 -> 184125.8
C112: GAS AND ELECTRISITY | E112: =+K104 -> 89111.26
C113: MAINTENANCE GENERAL | E113: =+L104 -> 24235.63
...

Sheet  EXPENSES HOUSE
A1: LANDCO BANK EXPENSES PER HOUSE
C3: SHARED | D3: SALARIES | E3: EXPENSES BY GUESTS | F3: BAIT SKIPPERS CLEANING | G3: RONNY SHORT ON OVERTIME | H3: STEEL FOR SECURITY DOOR | I3: HOUSEHOLD EQUIPMENT | J3: PETROL & BATTERY | K3: TOTAL PERSONAL | L3: TOTAL | M3: SHARED EXPENSES | O3: SHARED
B4: CASA LUZ | C4: =+O19 -> 148623.21 | D4: =+' EXPENSES'!V104 -> 34786.96 | E4: =SUM(' EXPENSES'!V97:V100) -> 0 | K4: =SUM(D4:J4) -> 34786.96 | L4: =+C4+K4 -> 183410.17 | M4: SALARIES & WAGES | N4: =+' EXPENSES'!E108 -> 238169.6 | O4: =+N4/4 -> 59542.4
B5: CASA AURORA | C5: =+C4 -> 148623.21 | D5: =+' EXPENSES'!W104 -> 63095.36 | I5: =+' EXPENSES'!W81 -> 0 | K5: =SUM(D5:J5) -> 63095.36 | L5: =+C5+K5 -> 211718.57 | M5: CASUAL WORKERS AND FOOD ALLOWANCE | N5: 49000 | O5: =+N5/4 -> 12250
B6: CASA CAJU | C6: =+C5 -> 148623.21 | D6: =+' EXPENSES'!X30+' EXPENSES'!X34 -> 38090 | G6: =+' EXPENSES'!X91 -> 0 | H6: =+' EXPENSES'!X49 -> 10208 | J6: =+' EXPENSES'!X44+' EXPENSES'!X69 -> 0 | K6: =SUM(D6:J6) -> 48298 | L6: =+C6+K6 -> 196921.21 | M6: OFFICE AND BANK CHARGES | N6: 6850.56 | O6: =+N6/4 -> 1712.64
B7: CASA COCO | C7: =+C6 -> 148623.21 | D7: =+' EXPENSES'!Y104 -> 44850 | I7: =+' EXPENSES'!Y36 -> 0 | K7: =SUM(D7:J7) -> 44850 | L7: =+C7+K7 -> 193473.21 | M7: ADMIN CHARGES (BDO & ANDRISA ENS ) | N7: 184125.8 | O7: =+N7/4 -> 46031.45
L8: =SUM(L4:L7) -> 785523.17 | M8: GAS AND ELECTRISITY | N8: 89111.26 | O8: =+N8/4 -> 22277.815
L9: =+' EXPENSES'!E4 -> 785523.17 | M9: MAINTENANCE GENERAL | N9: 24235.63 | O9: =+N9/4 -> 6058.9075
L10: =+L8-L9 -> 0 | M10: MAINTENANCE GARDEN & POOL | N10: 0 | O10: =+N10/4 -> 0
M11: SMALL TOOLS | N11: 0 | O11: =+N11/4 -> 0
M12: EQUIPMENT PRESSURE PUMP X 2 | N12: 0 | O12: =+N12/4 -> 0
M13: MAINTENANCE VEHICLES | N13: 0 | O13: =+N13/4 -> 0
M14: INSURANCE & LICENSE | O14: =+N14/4 -> 0
M15: DIESEL AND PETROL | N15: 0 | O15: =+N15/4 -> 0
M16: HOUSE KEEPING | N16: 0 | O16: =+N16/4 -> 0
M17: MARINTINE & MUNICIPAL TAXES IPRA &TAE | N17: 0 | O17: =+N17/4 -> 0
M18: COMMUNITY DONATION | N18: 3000 | O18: =+N18/4 -> 750
N19: =SUM(N4:N18) -> 594492.85 | O19: =SUM(O4:O18) -> 148623.21
M24: EXPENSES LUZ | N24: =+' EXPENSES'!V104 -> 34786.96 | O24: =+N24 -> 34786.96
M25: EXPENSES AURORA | N25: =+' EXPENSES'!E124 -> 63095.36 | O25: =+N25 -> 63095.36
M26: EXPENSES CAJU | N26: =+' EXPENSES'!E125 -> 48298 | O26: =+N26 -> 48298
M27: EXPENSES COCO | N27: =+' EXPENSES'!Y104 -> 44850 | O27: =+N27 -> 44850
N28: =+N19+N24+N25+N26+N27 -> 785523.17
N30: =+' EXPENSES'!E128 -> 785523.17
N31: =+N28-N30 -> 0

Sheet MONTHLY FOR THE YEAR
A1: LANDCO EXPENSES
B2: MONTH | C2: EXPENSES | D2: 63.25
B4: 46023 | C4: =+' EXPENSES'!E128 -> 785523.17 | D4: =+C4/$D$2 -> 12419.339
B5: 46055 | D5: =+C5/$D$2 -> 0
B6: 46087 | D6: =+C6/$D$2 -> 0
B7: 46119 | D7: =+C7/$D$2 -> 0
B8: 46151 | D8: =+C8/$D$2 -> 0
B9: 46183 | D9: =+C9/$D$2 -> 0
B10: 46215 | D10: =+C10/$D$2 -> 0
B11: 46247 | D11: =+C11/$D$2 -> 0
B12: 46279 | D12: =+C12/$D$2 -> 0
B13: 46311 | D13: =+C13/$D$2 -> 0
B14: 46343 | D14: =+C14/$D$2 -> 0
B15: 46375 | D15: =+C15/$D$2 -> 0
C16: =SUM(C4:C15) -> 785523.17 | D16: =SUM(D4:D15) -> 12419.339
B18: AVERAGE | C18: =+C16/9 -> 87280.352 | D18: =+D16/9 -> 1379.9265
